exploralytics/__init__.py
exploralytics/visualize/__init__.py
exploralytics/visualize/utils.py
exploralytics/visualize/visualizer.py
exploralytics-1.0.1.dist-info/LICENSE
exploralytics-1.0.1.dist-info/METADATA
exploralytics-1.0.1.dist-info/WHEEL
exploralytics-1.0.1.dist-info/top_level.txt
exploralytics-1.0.1.dist-info/RECORD
