Metadata-Version: 2.2
Name: exploralytics
Version: 1.0.1
Summary: A plotly-based toolkit for data exploration and visualization
Author-email: John Paul Curada <johncurada.work@gmail.com>
License: BSD License
Project-URL: Bug Tracker, https://github.com/jpcurada/exploralytics/issues
Project-URL: Source Code, https://github.com/jpcurada/exploralytics
Project-URL: Documentation, https://exploralytics.readthedocs.io
Keywords: data,visualization,plotly,analytics,eda,subplot
Classifier: Development Status :: 3 - Alpha
Classifier: Intended Audience :: Science/Research
Classifier: Programming Language :: Python :: 3
Classifier: Programming Language :: Python :: 3.9
Classifier: License :: OSI Approved :: BSD License
Classifier: Operating System :: OS Independent
Classifier: Topic :: Scientific/Engineering :: Visualization
Requires-Python: >=3.9
License-File: LICENSE
Requires-Dist: pandas>=1.3.0
Requires-Dist: plotly>=5.0.0
Requires-Dist: numpy>=1.20.0
Requires-Dist: plotly-express>=0.4.0
